Workbook

Sheet 見積書
AQ1: =TODAY() -> 46283
AC3: 様 | AQ3: No.1
B6: この度はご照会いただき誠にありがとうございます。下記の通りお見積り申し上げます。
B7: 何卒御下命の栄を賜りますようお願い申し上げます。 | AK7: 適格請求書登録番号：T3480001010237
B9: 御見積書
K16: 御見積金額 | U16: =AL19*1.1 -> 0 | AM16: 円也
AF19: 税抜き価格 | AL19: =工事内訳書!AT20 -> 0 | AU19: 円
AF21: 消費税（税率10％） | AM21: =AL19*0.1 -> 0 | AU21: 円
J26: ※見積条件書は必ずご確認ください。
C27: 工事名 | AG27: 株式会社 迅翔興業
C29: 工事場所 | AG29: 〒770-0944 | AM29: 徳島市南昭和町1丁目23 三谷第一ビル6Ｆ3
C31: 工期予定 | AF31: TEL 088-676-2192 | AP31: FAX 088-677-3042
C33: 見積有効期限 | J33: 1カ月 | AF33: ご不明な点がございましたらお気軽にお問合せください。 | AV33: 担当：桑原

Sheet 工事内訳書
AR1: =TODAY() -> 46283
C2: 工 事 内 訳 書
AR3: No.2
B4: =見積書!J27 -> 0
B6: NO | D6: 名称 | P6: 仕様 | AB6: 数量 | AG6: 単位 | AJ6: 単価 | AT6: 金額
B8: 1 | D8: 足場工 | AB8: 1 | AG8: 式 | AT8: =内訳明細書!M15 -> 0
B9: 2 | D9: 諸経費 | AB9: 1 | AG9: 式 | AT9: =内訳明細書!H21 -> 0
B10: 3 | D10: 運搬費 | AB10: 1 | AG10: 式 | AT10: =内訳明細書!M16 -> 0
B11: 4 | D11: 調整費 | AB11: 1 | AG11: 式 | AT11: =内訳明細書!M20 -> 0
D20: 合計 | AT20: =SUM(AT8:BC19) -> 0
B21: 御見積条件
B22: ・作業時間は昼勤8：00～17：00 夜勤作業無し
B23: ・足場数量、使用期間、作業計画の変更が発生した場合は再見積り願います。※重要
B24: ・過度な破損、汚れ、滅失は別途請求申し上げますのでご了承願います。
B25: ・見積りにない作業は別途見積り願います。
B26: ・上記以外の事項につきましては、別途両者にて協議お願い致します。

Sheet 内訳明細書
K1: =TODAY() -> 46283
B2: 内 訳 明 細 書
K3: NO.3
B4: =見積書!J27 -> 0
A6: NO | B6: 名称 | C6: 仕様 | F6: 数量 | G6: 単位 | H6: 設置 期間 | I6: 材料費 | K6: 労務費 | M6: 合計
I7: 単価 | J7: 合計 | K7: 単価 | L7: 合計 | M7: 単価 | N7: 総計
J8: =F8*I8 -> 0 | L8: =ROUND(F8*K8,0) -> 0 | M8: =K8+I8 -> 0 | N8: =L8+J8 -> 0 | R8: L1 | T8: L2 | X8: 面 | Z8: 高さ
J9: =F9*I9 -> 0 | L9: =ROUND(F9*K9,0) -> 0 | M9: =K9+I9 -> 0 | N9: =L9+J9 -> 0 | R9: 21.25 | S9: + | T9: 37.1 | U9: ＝ | V9: =R9+T9 -> 58.35 | W9: × | X9: 2 | Y9: × | AA9: ＝ | AB9: =V9*X9*Z9 -> 0
J10: =F10*I10 -> 0 | L10: =ROUND(F10*K10,0) -> 0 | M10: =K10+I10 -> 0 | N10: =L10+J10 -> 0 | R10: 1.8 | S10: + | T10: 1.8 | U10: ＝ | V10: =R10+T10 -> 3.6 | W10: × | X10: 2 | Y10: × | AA10: ＝ | AB10: =V10*X10*Z10 -> 0
J11: =F11*I11 -> 0 | L11: =ROUND(F11*K11,0) -> 0 | M11: =K11+I11 -> 0 | N11: =L11+J11 -> 0 | S11: + | U11: ＝ | V11: =R11+T11 -> 0 | W11: × | X11: 2 | Y11: × | AA11: ＝ | AB11: =V11*X11*Z11 -> 0
J12: =F12*I12 -> 0 | L12: =ROUND(F12*K12,0) -> 0 | M12: =K12+I12 -> 0 | N12: =L12+J12 -> 0 | R12: 15.9 | S12: + | T12: 4.5 | U12: ＝ | V12: =R12+T12 -> 20.4 | W12: × | X12: 2 | Y12: × | Z12: 5 | AA12: ＝ | AB12: =V12*X12*Z12 -> 204
J13: =F13*I13 -> 0 | L13: =ROUND(F13*K13,0) -> 0 | M13: =K13+I13 -> 0 | N13: =L13+J13 -> 0 | S13: + | U13: ＝ | V13: =R13+T13 -> 0 | W13: × | X13: 2 | Y13: × | Z13: 5 | AA13: ＝ | AB13: =V13*X13*Z13 -> 0
J14: =F14*I14 -> 0 | L14: =ROUND(F14*K14,0) -> 0 | M14: =K14+I14 -> 0 | N14: =L14+J14 -> 0 | S14: + | U14: ＝ | V14: =R14+T14 -> 0 | W14: × | Y14: × | AA14: ＝ | AB14: =V14*X14*Z14 -> 0
B15: 小計 | I15: =SUM(J8:J14) -> 0 | K15: =SUM(L8:L14) -> 0 | M15: =SUM(N8:O14) -> 0 | S15: + | U15: ＝ | V15: =R15+T15 -> 0 | W15: × | Y15: × | AA15: ＝ | AB15: =V15*X15*Z15 -> 0
B16: 運搬費（掛払） | F16: =F9+F10+F12 -> 0 | G16: ㎡ | M16: =F16*H16 -> 0 | S16: + | U16: ＝ | V16: =R16+T16 -> 0 | W16: × | Y16: × | AA16: ＝ | AB16: =V16*X16*Z16 -> 0
B17: 法定福利費 | C17: 労務費 | F17: 15.9 | G17: ％ | M17: =K15*F17% -> 0 | AB17: =SUM(AB9:AB16) -> 204
B18: 諸経費 | C18: 工事金額 | F18: 5 | G18: ％ | M18: =M15*F18% -> 0
B19: 消耗品 | C19: 工事金額 | F19: 1 | G19: ％ | M19: =M15*F19% -> 0
B20: 調整費 | F20: 1 | G20: 式
B21: 経費合計 | F21: 1 | G21: 式 | H21: =SUM(M17:O19) -> 0
B22: 総合計 | C22: =IFERROR(SUM(M15+H21+M20+M16),"") -> 0 | O22: 円 | R22: =C22/F16 -> #DIV/0!
I33: 9
